papertty/__init__.py
papertty/drivers/LICENSE
papertty/drivers/README.md
papertty/drivers/__init__.py
papertty/drivers/driver_it8951.py
papertty/drivers/drivers_4in2.py
papertty/drivers/drivers_base.py
papertty/drivers/drivers_color.py
papertty/drivers/drivers_colordraw.py
papertty/drivers/drivers_consts.py
papertty/drivers/drivers_full.py
papertty/drivers/drivers_partial.py
papertty/papertty.py
papertty/resources/nanofont.pbm
papertty/resources/nanofont.pil
papertty/resources/papertty.service
papertty/resources/start.sh
papertty/resources/tom-thumb.pbm
papertty/resources/tom-thumb.pil
papertty-0.1.8.dist-info/entry_points.txt
papertty-0.1.8.dist-info/WHEEL
papertty-0.1.8.dist-info/METADATA
papertty-0.1.8.dist-info/RECORD
