Metadata-Version: 2.1
Name: papertty
Version: 0.1.8
Summary: Python module to render a TTY or VNC on e-ink
Home-page: https://github.com/joukos/PaperTTY
Author: Jouko Strömmer
Author-email: jouko.strommer@iki.fi
Requires-Python: >=3.5,<4.0
Classifier: Programming Language :: Python :: 3
Classifier: Programming Language :: Python :: 3.5
Classifier: Programming Language :: Python :: 3.6
Classifier: Programming Language :: Python :: 3.7
Classifier: Programming Language :: Python :: 3.8
Requires-Dist: Pillow (==7.1.2)
Requires-Dist: RPi.GPIO (>=0.7.0,<0.8.0)
Requires-Dist: click (>=7.1.2,<8.0.0)
Requires-Dist: spidev (>=3.4,<4.0)
Requires-Dist: vncdotool (>=1.0.0,<2.0.0)
Project-URL: Repository, https://github.com/joukos/PaperTTY
